LICENSE
README.md
setup.py
rc_protocol/__init__.py
rc_protocol/rc_protocol.py
rc_protocol.egg-info/PKG-INFO
rc_protocol.egg-info/SOURCES.txt
rc_protocol.egg-info/dependency_links.txt
rc_protocol.egg-info/top_level.txt
test/__init__.py
test/main.py