Metadata-Version: 2.1
Name: rc-protocol
Version: 0.0.5
Summary: Implementation of random checksum protocol
Home-page: https://github.com/myOmikron/rcp/
Author: Niklas Pfister
Author-email: kontakt@omikron.dev
License: UNKNOWN
Platform: UNKNOWN
Classifier: Programming Language :: Python :: 3
Classifier: License :: OSI Approved :: GNU General Public License v2 or later (GPLv2+)
Classifier: Operating System :: OS Independent
Requires-Python: >2.7
License-File: LICENSE
